velora/__init__.py
velora/buffer/__init__.py
velora/buffer/base.py
velora/buffer/experience.py
velora/buffer/replay.py
velora/callbacks.py
velora/gym/__init__.py
velora/gym/search.py
velora/gym/wrap.py
velora/metrics/__init__.py
velora/metrics/db.py
velora/metrics/models.py
velora/models/__init__.py
velora/models/activation.py
velora/models/backbone.py
velora/models/base.py
velora/models/config.py
velora/models/lnn/__init__.py
velora/models/lnn/cell.py
velora/models/lnn/ncp.py
velora/models/lnn/sparse.py
velora/models/nf/__init__.py
velora/models/nf/agent.py
velora/models/nf/modules.py
velora/models/sac/__init__.py
velora/models/sac/continuous.py
velora/models/sac/discrete.py
velora/models/weight.py
velora/state.py
velora/time.py
velora/training/__init__.py
velora/training/display.py
velora/training/handler.py
velora/training/metrics.py
velora/utils/__init__.py
velora/utils/capture.py
velora/utils/core.py
velora/utils/format.py
velora/utils/restore.py
velora/utils/torch.py
velora/wiring.py
velora-0.2.0.dist-info/LICENSE
velora-0.2.0.dist-info/METADATA
velora-0.2.0.dist-info/WHEEL
velora-0.2.0.dist-info/RECORD
