Metadata-Version: 2.3
Name: velora
Version: 0.2.0
Summary: A Liquid Reinforcement Learning (RL) framework.
License: MIT
Author: Ryan Partridge
Author-email: rpartridge101@gmail.com>
Requires-Python: >=3.11,<4.0
Classifier: Development Status :: 4 - Beta
Classifier: Intended Audience :: Developers
Classifier: License :: OSI Approved :: MIT License
Classifier: Natural Language :: English
Classifier: Operating System :: OS Independent
Classifier: Programming Language :: Python
Classifier: Programming Language :: Python :: 3
Classifier: Programming Language :: Python :: 3.11
Classifier: Programming Language :: Python :: 3.12
Classifier: Programming Language :: Python :: 3.13
Classifier: Topic :: Scientific/Engineering :: Artificial Intelligence
Classifier: Topic :: Software Development
Classifier: Topic :: Software Development :: Libraries :: Python Modules
Provides-Extra: all
Provides-Extra: comet
Provides-Extra: viz
Requires-Dist: comet-ml (>=3.49.5,<4.0.0) ; extra == "all"
Requires-Dist: comet-ml (>=3.49.5,<4.0.0) ; extra == "comet"
Requires-Dist: gymnasium[box2d,classic-control,mujoco,other] (>=1.1.1,<2.0.0)
Requires-Dist: plotly (>=6.0.0,<7.0.0)
Requires-Dist: pydantic (>=2.10.6,<3.0.0)
Requires-Dist: pydantic-settings (>=2.8.1,<3.0.0)
Requires-Dist: safetensors (>=0.5.3,<0.6.0)
Requires-Dist: scikit-learn (>=1.6.1,<2.0.0) ; extra == "all"
Requires-Dist: scikit-learn (>=1.6.1,<2.0.0) ; extra == "viz"
Requires-Dist: sqlmodel (>=0.0.24,<1.0.0)
Project-URL: Documentation, https://velora.achronus.dev
Project-URL: Repository, https://github.com/Achronus/velora
Project-URL: issues, https://github.com/Achronus/velora/issues
